munet/__init__.py
munet/__main__.py
munet/args.py
munet/base.py
munet/cleanup.py
munet/cli.py
munet/compat.py
munet/config.py
munet/kinds.yaml
munet/linux.py
munet/logconf-mutest.yaml
munet/logconf.yaml
munet/mucmd.py
munet/mulog.py
munet/munet-schema.json
munet/mutestshare.py
munet/mutini.py
munet/native.py
munet/parser.py
munet/watchlog.py
munet/mutest/__main__.py
munet/mutest/userapi.py
munet/testing/__init__.py
munet/testing/fixtures.py
munet/testing/hooks.py
munet/testing/util.py
munet-0.17.3.dist-info/METADATA
munet-0.17.3.dist-info/WHEEL
munet-0.17.3.dist-info/entry_points.txt
munet-0.17.3.dist-info/licenses/LICENSE.md
munet-0.17.3.dist-info/RECORD
