Metadata-Version: 2.4
Name: munet
Version: 0.17.3
Summary: A package to facilitate network simulations
Project-URL: Repository, https://github.com/LabNConsulting/munet
Author-email: Christian Hopps <chopps@labn.net>
License: GPL-2.0-or-later
License-File: LICENSE.md
Requires-Python: >=3.9
Requires-Dist: deepdiff<8.0.0,>=6.2.1
Requires-Dist: jsonschema>=4.23.0
Requires-Dist: pexpect>=4.9.0
Requires-Dist: pyyaml>=6.0.3
